CHANGELOG.md
CODE_OF_CONDUCT.md
MANIFEST.in
README.md
requirements-test.txt
requirements.txt
setup.py
fiber/__init__.py
fiber/backend.py
fiber/cli.py
fiber/config.py
fiber/context.py
fiber/core.py
fiber/docker_backend.py
fiber/init.py
fiber/kubernetes_backend.py
fiber/local_backend.py
fiber/managers.py
fiber/meta.py
fiber/pool.py
fiber/popen_fiber_spawn.py
fiber/process.py
fiber/queues.py
fiber/socket.py
fiber/spawn.py
fiber/util.py
fiber.egg-info/PKG-INFO
fiber.egg-info/SOURCES.txt
fiber.egg-info/dependency_links.txt
fiber.egg-info/entry_points.txt
fiber.egg-info/not-zip-safe
fiber.egg-info/requires.txt
fiber.egg-info/top_level.txt
fiber/experimental/__init__.py
fiber/experimental/ring.py
tests/__init__.py
tests/test_backend.py
tests/test_config.py
tests/test_docker_backend.py
tests/test_managers.py
tests/test_misc.py
tests/test_pool.py
tests/test_popen.py
tests/test_process.py
tests/test_process_misc.py
tests/test_queue.py