Metadata-Version: 2.1
Name: fiber
Version: 0.2.0
Summary: A distributed computing library for modern computer clusters
Home-page: https://github.com/uber/fiber
Author: Jiale Zhi
Author-email: jiale@uber.com
License: Apache 2.0
Platform: UNKNOWN
Classifier: License :: OSI Approved :: Apache Software License
Classifier: Programming Language :: Python :: 3
Classifier: Topic :: System :: Distributed Computing
Provides-Extra: test
